vws/__init__.py
vws/workspace.py
vws-0.2.dist-info/METADATA
vws-0.2.dist-info/WHEEL
vws-0.2.dist-info/top_level.txt
vws-0.2.dist-info/RECORD
