Metadata-Version: 2.1
Name: vws
Version: 0.2
Summary: Consists of three main classes: File, Directory, and Workspace. Together, these classes allow users to create, manage, and organize files and directories in a virtual workspace.
Home-page: https://github.com/Akicuo/VirtualWorkspace
Author: Lyan
Author-email: admin@blackcoffee.lol
Classifier: Programming Language :: Python :: 3
Classifier: Operating System :: OS Independent
Requires-Python: >=3.6
